VideoJoin/__init__.py
VideoJoin/__main__.py
VideoJoin/cli.py
videojoin-1.0.2.dist-info/METADATA
videojoin-1.0.2.dist-info/WHEEL
videojoin-1.0.2.dist-info/entry_points.txt
videojoin-1.0.2.dist-info/top_level.txt
videojoin-1.0.2.dist-info/RECORD
