Metadata-Version: 2.4
Name: VideoJoin
Version: 1.0.2
Summary: VideoJoin is a lightweight command-line tool for concatenating two video files (MP4, MOV, MKV, AVI, M4V) while preserving original audio and video quality using FFmpeg.
Author-email: Wilgat Wong <wilgat.wong@gmail.com>
License: MIT
Project-URL: Homepage, https://github.com/Wilgat/VideoJoin
Project-URL: Repository, https://github.com/Wilgat/VideoJoin
Project-URL: Issues, https://github.com/Wilgat/VideoJoin/issues
Keywords: Video Editing,Video,Multimedia
Requires-Python: !=3.0.*,!=3.1.*,!=3.2.*,!=3.3.*,!=3.4.*,>=2.7
Requires-Dist: ChronicleLogger>=1.2.3
